pytest_schema/__init__.py
pytest_schema/helpers.py
pytest_schema/match.py
pytest_schema/schema.py
pytest_schema/types.py
pytest_schema-0.1.2.dist-info/LICENSE
pytest_schema-0.1.2.dist-info/METADATA
pytest_schema-0.1.2.dist-info/WHEEL
pytest_schema-0.1.2.dist-info/entry_points.txt
pytest_schema-0.1.2.dist-info/top_level.txt
pytest_schema-0.1.2.dist-info/RECORD
